flame_data/__init__.py
flame_data/cavity_data/EQ7_curve.lat
flame_data/cavity_data/S4_curve.lat
flame_data/cavity_data/axisData_29.txt
flame_data/cavity_data/axisData_41.txt
flame_data/cavity_data/axisData_53.txt
flame_data/cavity_data/axisData_5cell.txt
flame_data/cavity_data/axisData_85.txt
flame_data/cavity_data/rebuncher_38.lat
flame_data/cavity_data/rebuncher_38_p.lat
flame_data/cavity_data/thinlenlon_29.lat
flame_data/cavity_data/thinlenlon_29_p.lat
flame_data/cavity_data/thinlenlon_41.lat
flame_data/cavity_data/thinlenlon_41_p.lat
flame_data/cavity_data/thinlenlon_53.lat
flame_data/cavity_data/thinlenlon_53_p.lat
flame_data/cavity_data/thinlenlon_7g.lat
flame_data/cavity_data/thinlenlon_85.lat
flame_data/cavity_data/thinlenlon_85_p.lat
flame_data/cavity_data/triplet_curve.lat
flame_data/cavity_data/Multipole29/CaviMlp_29.txt
flame_data/cavity_data/Multipole29/thinlenlon_29.txt
flame_data/cavity_data/Multipole41/CaviMlp_41.txt
flame_data/cavity_data/Multipole41/thinlenlon_41.txt
flame_data/cavity_data/Multipole53/CaviMlp_53.txt
flame_data/cavity_data/Multipole53/thinlenlon_53.txt
flame_data/cavity_data/Multipole85/CaviMlp_85.txt
flame_data/cavity_data/Multipole85/thinlenlon_85.txt
flame_data-1.7.4.post1.dist-info/LICENSE
flame_data-1.7.4.post1.dist-info/METADATA
flame_data-1.7.4.post1.dist-info/WHEEL
flame_data-1.7.4.post1.dist-info/top_level.txt
flame_data-1.7.4.post1.dist-info/RECORD
